Metadata-Version: 2.1
Name: banga
Version: 0.1.0
Summary: Unified Bengali Tools Package
Author: Forhad Khan (forhadakhan)
Classifier: Programming Language :: Python :: 3
Classifier: License :: OSI Approved :: MIT License
Classifier: Operating System :: OS Independent
